{
    "schema": [
        {
            "name": "mAdminState", 
            "default": "enabled", 
            "type": {
                "href": "/mgmt/types/default/dmAdminState"
            }, 
            "summary": "Set the administrative state of this configuration.", 
            "/mgmt/types/default/dmAdminState": {
                "type": {
                    "cli-arg": "enabled | disabled", 
                    "name": "dmAdminState", 
                    "value-list": {
                        "value": [
                            {
                                "name": "enabled", 
                                "display": "enabled"
                            }, 
                            {
                                "name": "disabled", 
                                "display": "disabled"
                            }
                        ]
                    }
                }, 
                "_links": {
                    "doc": {
                        "href": "/mgmt/docs/types/dmAdminState"
                    }, 
                    "self": {
                        "href": "/mgmt/types/default/dmAdminState"
                    }
                }
            }, 
            "label": "Enable administrative state", 
            "cli-alias": "admin-state", 
            "display": "Administrative state", 
            "hoverhelp": "&lt;p>Set the administrative state of the configuration.&lt;/p>&lt;ul>&lt;li>To make active, set the check box.&lt;/li>&lt;li>To make inactive, clear the check box.&lt;/li>&lt;/ul>", 
            "description": "&lt;p>The administrative state of the configuration.&lt;/p>&lt;ul>&lt;li>To make active, set to enabled.&lt;/li>&lt;li>To make inactive, set to disabled.&lt;/li>&lt;/ul>"
        }, 
        {
            "/mgmt/types/default/dmString": {
                "type": {
                    "cli-arg": "string", 
                    "name": "dmString"
                }, 
                "_links": {
                    "doc": {
                        "href": "/mgmt/docs/types/dmString"
                    }, 
                    "self": {
                        "href": "/mgmt/types/default/dmString"
                    }
                }
            }, 
            "name": "UserSummary", 
            "cli-alias": "summary", 
            "summary": "Brief summary for user annotation.", 
            "type": {
                "href": "/mgmt/types/default/dmString"
            }, 
            "display": "Comments"
        }, 
        {
            "/mgmt/types/default/dmLocalIPHostAddress": {
                "type": {
                    "cli-arg": "dotted-ip or 0 for any", 
                    "name": "dmLocalIPHostAddress", 
                    "format": "(a.b.c.d or 0 for any)"
                }, 
                "_links": {
                    "doc": {
                        "href": "/mgmt/docs/types/dmLocalIPHostAddress"
                    }, 
                    "self": {
                        "href": "/mgmt/types/default/dmLocalIPHostAddress"
                    }
                }
            }, 
            "name": "LocalAddress", 
            "default": "0.0.0.0", 
            "type": {
                "href": "/mgmt/types/default/dmLocalIPHostAddress"
            }, 
            "required": "true", 
            "summary": "Local address", 
            "cli-alias": "address", 
            "display": "Local Address", 
            "description": "&lt;p>Specify the IPv4 or IPv6 address or the host alias on which the Target Control Service listens. The default of 0.0.0.0 indicates that the service is active on all IPv4 addresses.&lt;/p>"
        }, 
        {
            "name": "Priority", 
            "default": "normal", 
            "type": {
                "href": "/mgmt/types/default/dmSchedulerPriority"
            }, 
            "/mgmt/types/default/dmSchedulerPriority": {
                "type": {
                    "name": "dmSchedulerPriority", 
                    "value-list": {
                        "value": [
                            {
                                "name": "unknown", 
                                "display": "unknown"
                            }, 
                            {
                                "name": "high-min", 
                                "display": "high-min"
                            }, 
                            {
                                "summary": "", 
                                "display": "High", 
                                "name": "high", 
                                "description": "A service or transaction assigned this priority setting will receive above normal scheduling priority and resource allocation."
                            }, 
                            {
                                "name": "high-max", 
                                "display": "high-max"
                            }, 
                            {
                                "name": "normal-min", 
                                "display": "normal-min"
                            }, 
                            {
                                "summary": "", 
                                "display": "Normal", 
                                "name": "normal", 
                                "description": "A service or transaction assigned this priority setting will receive normal scheduling priority and resource allocation."
                            }, 
                            {
                                "name": "normal-max", 
                                "display": "normal-max"
                            }, 
                            {
                                "name": "low-min", 
                                "display": "low-min"
                            }, 
                            {
                                "summary": "", 
                                "display": "Low", 
                                "name": "low", 
                                "description": "A service or transaction assigned this priority setting will receive below normal scheduling priority and resource allocation."
                            }, 
                            {
                                "name": "low-max", 
                                "display": "low-max"
                            }
                        ]
                    }, 
                    "display": "Transaction Priority"
                }, 
                "_links": {
                    "doc": {
                        "href": "/mgmt/docs/types/dmSchedulerPriority"
                    }, 
                    "self": {
                        "href": "/mgmt/types/default/dmSchedulerPriority"
                    }
                }
            }, 
            "summary": "Service-scheduling priority", 
            "cli-alias": "priority", 
            "display": "Service priority", 
            "description": "Select the service scheduling priority. When system resources are in high demand, \"high\" priority services are favored over lower priority services."
        }, 
        {
            "name": "LocalPort", 
            "cli-alias": "local-port", 
            "required": "true", 
            "maximum": "0xFFFF", 
            "summary": "Local listening port", 
            "listener": "LocalAddress", 
            "minimum": 1, 
            "type": {
                "href": "/mgmt/types/default/dmIPPort"
            }, 
            "/mgmt/types/default/dmIPPort": {
                "type": {
                    "cli-arg": "ip-port", 
                    "minimum": 0, 
                    "name": "dmIPPort", 
                    "maximum": "0xFFFF"
                }, 
                "_links": {
                    "doc": {
                        "href": "/mgmt/docs/types/dmIPPort"
                    }, 
                    "self": {
                        "href": "/mgmt/types/default/dmIPPort"
                    }
                }
            }, 
            "display": "Local port", 
            "description": "Specify the local listening port for the service."
        }, 
        {
            "/mgmt/types/default/dmString": {
                "type": {
                    "cli-arg": "string", 
                    "name": "dmString"
                }, 
                "_links": {
                    "doc": {
                        "href": "/mgmt/docs/types/dmString"
                    }, 
                    "self": {
                        "href": "/mgmt/types/default/dmString"
                    }
                }
            }, 
            "description": "Specify the Service Name of the enterprise application to connect to. This corresponds to a back-end Service Name defined on the Cloud Gateway in the enterprise.", 
            "minimum-length": 1, 
            "type": {
                "href": "/mgmt/types/default/dmString"
            }, 
            "required": "true", 
            "summary": "Name of the service, or enterprise application, to connect to.", 
            "maximum-length": 255, 
            "cli-alias": "service-name", 
            "display": "Service Name", 
            "name": "ServiceName"
        }, 
        {
            "name": "RemoteAddress", 
            "cli-alias": "remote-address", 
            "required": "true", 
            "summary": "Hostname or IP address of the Cloud Gateway.", 
            "/mgmt/types/default/dmHostname": {
                "type": {
                    "cli-arg": "dotted-ip or hostname", 
                    "name": "dmHostname", 
                    "format": "(a.b.c.d or hostname)"
                }, 
                "_links": {
                    "doc": {
                        "href": "/mgmt/docs/types/dmHostname"
                    }, 
                    "self": {
                        "href": "/mgmt/types/default/dmHostname"
                    }
                }
            }, 
            "type": {
                "href": "/mgmt/types/default/dmHostname"
            }, 
            "display": "Cloud Gateway address", 
            "description": "Specify the hostname or IP address of the remote server."
        }, 
        {
            "name": "RemotePort", 
            "/mgmt/types/default/dmIPPort": {
                "type": {
                    "cli-arg": "ip-port", 
                    "minimum": 0, 
                    "name": "dmIPPort", 
                    "maximum": "0xFFFF"
                }, 
                "_links": {
                    "doc": {
                        "href": "/mgmt/docs/types/dmIPPort"
                    }, 
                    "self": {
                        "href": "/mgmt/types/default/dmIPPort"
                    }
                }
            }, 
            "required": "true", 
            "maximum": "0xFFFF", 
            "summary": "Listening port on the Cloud Gateway", 
            "minimum": 1, 
            "type": {
                "href": "/mgmt/types/default/dmIPPort"
            }, 
            "cli-alias": "remote-port", 
            "display": "Cloud Gateway port", 
            "description": "Specify the listening port number of the Cloud Gateway."
        }, 
        {
            "name": "SSLProxy", 
            "type": {
                "href": "/mgmt/types/default/dmReference", 
                "reference-to": {
                    "href": "/mgmt/metadata/default/SSLProxyProfile"
                }
            }, 
            "required": "true", 
            "summary": "TLS proxy profile to secure connections", 
            "cli-alias": "ssl", 
            "display": "TLS proxy profile", 
            "/mgmt/types/default/dmReference": {
                "type": {
                    "cli-arg": "object", 
                    "name": "dmReference"
                }, 
                "_links": {
                    "doc": {
                        "href": "/mgmt/docs/types/dmReference"
                    }, 
                    "self": {
                        "href": "/mgmt/types/default/dmReference"
                    }
                }
            }, 
            "description": "Select a TLS proxy profile to manage TLS communications with the peers. The TLS proxy profile identifies the keys and certificates for the handshake."
        }, 
        {
            "name": "FrontTimeout", 
            "default": 0, 
            "type": {
                "href": "/mgmt/types/default/dmTimeInterval"
            }, 
            "required": "true", 
            "maximum": 86400, 
            "summary": "Maximum idle time for client connections in a transaction", 
            "/mgmt/types/default/dmTimeInterval": {
                "type": {
                    "cli-arg": "seconds", 
                    "minimum": 0, 
                    "name": "dmTimeInterval", 
                    "maximum": "0xFFFFFFFF"
                }, 
                "_links": {
                    "doc": {
                        "href": "/mgmt/docs/types/dmTimeInterval"
                    }, 
                    "self": {
                        "href": "/mgmt/types/default/dmTimeInterval"
                    }
                }
            }, 
            "minimum": 0, 
            "units": "Seconds", 
            "cli-alias": "front-timeout", 
            "display": "Client-side timeout", 
            "description": "Specify the maximum idle time for client connections in a transaction. This timer monitors the idle time in the data transfer process. If the specified idle time is exceeded, the connection is torn down. Enter a value in the range 0 - 86400. The value of 0 indicates that the timer is disabled. The default value is 0."
        }, 
        {
            "name": "BackTimeout", 
            "default": 0, 
            "type": {
                "href": "/mgmt/types/default/dmTimeInterval"
            }, 
            "required": "true", 
            "maximum": 86400, 
            "summary": "Maximum idle time for the Cloud Gateway connection in a transaction", 
            "/mgmt/types/default/dmTimeInterval": {
                "type": {
                    "cli-arg": "seconds", 
                    "minimum": 0, 
                    "name": "dmTimeInterval", 
                    "maximum": "0xFFFFFFFF"
                }, 
                "_links": {
                    "doc": {
                        "href": "/mgmt/docs/types/dmTimeInterval"
                    }, 
                    "self": {
                        "href": "/mgmt/types/default/dmTimeInterval"
                    }
                }
            }, 
            "minimum": 0, 
            "units": "Seconds", 
            "cli-alias": "back-timeout", 
            "display": "Gateway-side timeout", 
            "description": "Specify the maximum idle time for Cloud Gateway connections in a transaction. This timer monitors the idle time in the data transfer process. If the specified idle time is exceeded, the connection is torn down. Enter a value in the range 0 - 86400. The value of 0 indicates that the timer is disabled. The default value is 0."
        }, 
        {
            "name": "ConnTimeout", 
            "default": 0, 
            "type": {
                "href": "/mgmt/types/default/dmTimeInterval"
            }, 
            "required": "true", 
            "maximum": 86400, 
            "summary": "Maximum duration for transactions", 
            "/mgmt/types/default/dmTimeInterval": {
                "type": {
                    "cli-arg": "seconds", 
                    "minimum": 0, 
                    "name": "dmTimeInterval", 
                    "maximum": "0xFFFFFFFF"
                }, 
                "_links": {
                    "doc": {
                        "href": "/mgmt/docs/types/dmTimeInterval"
                    }, 
                    "self": {
                        "href": "/mgmt/types/default/dmTimeInterval"
                    }
                }
            }, 
            "minimum": 0, 
            "units": "Seconds", 
            "cli-alias": "connection-timeout", 
            "display": "Transaction timeout", 
            "description": "Specify the maximum duration for transactions. This timer monitors the duration of end-to-end transactions. If the specified connection time is exceeded, the client connection is torn down. Enter a value in the range of 0 - 86400. The value of 0 indicates that the timer is disabled. The default value is 0."
        }, 
        {
            "/mgmt/types/default/dmUInt32": {
                "type": {
                    "cli-arg": "number", 
                    "minimum": 0, 
                    "name": "dmUInt32", 
                    "maximum": "0xFFFFFFFF"
                }, 
                "_links": {
                    "doc": {
                        "href": "/mgmt/docs/types/dmUInt32"
                    }, 
                    "self": {
                        "href": "/mgmt/types/default/dmUInt32"
                    }
                }
            }, 
            "name": "ConnLimit", 
            "default": 100, 
            "type": {
                "href": "/mgmt/types/default/dmUInt32"
            }, 
            "required": "true", 
            "maximum": 65535, 
            "summary": "Maximum number of concurrent client connections", 
            "minimum": 0, 
            "cli-alias": "maximum-connections", 
            "display": "Maximum client connections", 
            "description": "Specify the maximum number of concurrent client connections to the service. Enter a value in the range of 0 - 65535. The value of 0 indicates an unlimited number of connections. The default value is 100."
        }
    ]
}